endstone_disable_me/__init__.py
endstone_disable_me/plugin.py
endstone_disable_me-0.1.0.dist-info/METADATA
endstone_disable_me-0.1.0.dist-info/WHEEL
endstone_disable_me-0.1.0.dist-info/entry_points.txt
endstone_disable_me-0.1.0.dist-info/licenses/LICENSE
endstone_disable_me-0.1.0.dist-info/RECORD
