Metadata-Version: 2.4
Name: endstone-disable-me
Version: 0.1.0
Summary: A simple plugin to prevent /me command from execution
Project-URL: Homepage, https://github.com/endstone-essentials/disable-me
Author-email: Vincent Wu <magicdroidx@gmail.com>
License: MIT License
License-File: LICENSE
Keywords: endstone,plugin
